swarmauri_prompt_j2prompttemplate/J2PromptTemplate.py
swarmauri_prompt_j2prompttemplate/__init__.py
swarmauri_prompt_j2prompttemplate-0.7.3.dist-info/LICENSE
swarmauri_prompt_j2prompttemplate-0.7.3.dist-info/METADATA
swarmauri_prompt_j2prompttemplate-0.7.3.dist-info/WHEEL
swarmauri_prompt_j2prompttemplate-0.7.3.dist-info/RECORD
