Metadata-Version: 2.3
Name: swarmauri_prompt_j2prompttemplate
Version: 0.7.3
Summary: Jinja2 Prompt Template for Swarmauri.
License: Apache-2.0
Author: Jacob Stewart
Author-email: jacob@swarmauri.com
Requires-Python: >=3.10,<3.13
Classifier: License :: OSI Approved :: Apache Software License
Classifier: Programming Language :: Python :: 3.10
Classifier: Programming Language :: Python :: 3.11
Classifier: Programming Language :: Python :: 3.12
Requires-Dist: inflect (>=7.0.0)
Requires-Dist: jinja2 (>=3.1.6)
Requires-Dist: pydantic (>=1.8.2)
Requires-Dist: swarmauri_base
Requires-Dist: swarmauri_core
